pandalibs/__init__.py
pandalibs/pprint_nosort.py
pandalibs/yaml_importer.py
pandalibs-0.1.6.dist-info/METADATA
pandalibs-0.1.6.dist-info/WHEEL
pandalibs-0.1.6.dist-info/top_level.txt
pandalibs-0.1.6.dist-info/RECORD
