Metadata-Version: 2.1
Name: pandalibs
Version: 0.1.6
Summary: My personal library.
Author: nightpanda2810
Requires-Dist: pyyaml
